__init__.py
keyboardMac/__init__.py
keyboardMac/core.py
keyboardMac-0.0.4.dist-info/LICENSE
keyboardMac-0.0.4.dist-info/METADATA
keyboardMac-0.0.4.dist-info/WHEEL
keyboardMac-0.0.4.dist-info/top_level.txt
keyboardMac-0.0.4.dist-info/RECORD
