Metadata-Version: 2.1
Name: keyboardMac
Version: 0.0.4
Summary: A recreation of keyboard that works on macOS
Author-email: pirosowa <songpiano28@gmail.com>
Classifier: Programming Language :: Python :: 3
Classifier: License :: OSI Approved :: MIT License
Classifier: Operating System :: OS Independent
Requires-Python: >=3.7
License-File: LICENSE
